__init__.py
pyconst.py
pyenum.py
pyeprom.py
pyhelper.py
pyvisonic.py
examples/MessageDecoder.py
examples/__init__.py
examples/bridge.py
examples/complete_example.py
examples/simple_example.py
pyvisonic-3.0.0.dist-info/licenses/LICENSE
pyvisonic-3.0.0.dist-info/METADATA
pyvisonic-3.0.0.dist-info/WHEEL
pyvisonic-3.0.0.dist-info/top_level.txt
pyvisonic-3.0.0.dist-info/RECORD
