Metadata-Version: 2.4
Name: pyvisonic
Version: 3.0.0
Summary: An asyncio python interface library to the visonic alarm panel
Author-email: DaveSmegHead <davesmeghead@hotmail.com>
Project-URL: Homepage, https://github.com/davesmeghead/pyvisonic
Project-URL: Issues, https://github.com/davesmeghead/pyvisonic/Issues
Classifier: Programming Language :: Python :: 3
Classifier: License :: OSI Approved :: MIT License
Classifier: Operating System :: OS Independent
Requires-Python: >=3.13
License-File: LICENSE
Requires-Dist: aconsole==0.0.8
Requires-Dist: pyserial_asyncio==0.6
Requires-Dist: Pillow
Dynamic: license-file
